onnxdiff/__init__.py
onnxdiff/diff.py
onnxdiff/ort_infer.py
onnxdiff/structs_parameters.py
onnxdiff/utils.py
onnxdiffer-0.1.2.dist-info/LICENSE
onnxdiffer-0.1.2.dist-info/METADATA
onnxdiffer-0.1.2.dist-info/WHEEL
onnxdiffer-0.1.2.dist-info/entry_points.txt
onnxdiffer-0.1.2.dist-info/top_level.txt
onnxdiffer-0.1.2.dist-info/RECORD
