Metadata-Version: 2.1
Name: onnxdiffer
Version: 0.1.2
Summary: Comparison of onnx models by structure, parameters and onnxruntime
Home-page: https://github.com/Taot-chen/onnx-diff
Author: oehuosi
Author-email: oehuosi@oehuosi.com
Classifier: Programming Language :: Python
Classifier: Programming Language :: Python :: 3
Classifier: Programming Language :: Python :: 3.8
Classifier: Programming Language :: Python :: Implementation :: CPython
Classifier: Programming Language :: Python :: Implementation :: PyPy
Requires-Python: >=3.8
License-File: LICENSE
Requires-Dist: onnx<2.0.0,>=1.17.0
Requires-Dist: onnxruntime>=1.19.2
Requires-Dist: typing_extensions>=4.12.2
Requires-Dist: GraKeL<0.2.0,>=0.1.9
Requires-Dist: colorama<0.5.0,>=0.4.6
Requires-Dist: numpy<2.0.0,>=1.24.1
Requires-Dist: tabulate<0.10.0,>=0.9.0
Requires-Dist: dataclasses>=0.6
